TeleBotPlus/HTML.py
TeleBotPlus/__init__.py
TeleBotPlus/_module_info.py
TeleBotPlus/assets.py
TeleBotPlus/assets_converter.py
TeleBotPlus/lang.py
TeleBotPlus/main.py
TeleBotPlus/utils.py
TeleBotPlus/webhook.py
telebotplus-0.1.4.dist-info/METADATA
telebotplus-0.1.4.dist-info/WHEEL
telebotplus-0.1.4.dist-info/RECORD
