Metadata-Version: 2.1
Name: TeleBotPlus
Version: 0.1.4
Summary: Неофициальное дополнение к библиотеке pyTelegramBotAPI
Home-page: https://github.com/MainPlay-TG/TeleBotPlus.py
Author: MainPlay TG
Author-email: xbox.roman6666666666@gmail.com
Requires-Python: >=3.7,<4.0
Classifier: Programming Language :: Python :: 3
Classifier: Programming Language :: Python :: 3.7
Classifier: Programming Language :: Python :: 3.8
Classifier: Programming Language :: Python :: 3.9
Classifier: Programming Language :: Python :: 3.10
Classifier: Programming Language :: Python :: 3.11
Classifier: Programming Language :: Python :: 3.12
Requires-Dist: MainShortcuts2 (>=2.1.3,<3.0.0)
Requires-Dist: pyTelegramBotAPI (>=4.20.0,<5.0.0)
Requires-Dist: requests (>=2.32.3,<3.0.0)
Project-URL: Repository, https://github.com/MainPlay-TG/TeleBotPlus.py
